picpay/__init__.py
picpay/picpay.py
picpay_python-0.4.1.dist-info/LICENSE
picpay_python-0.4.1.dist-info/METADATA
picpay_python-0.4.1.dist-info/WHEEL
picpay_python-0.4.1.dist-info/top_level.txt
picpay_python-0.4.1.dist-info/RECORD
